esrnn/__init__.py
esrnn/forecasting_esrnn.py
esrnn/contrib/ESRNN.py
esrnn/contrib/ESRNN_auto.py
esrnn/contrib/__init__.py
esrnn/contrib/utils/DRNN.py
esrnn/contrib/utils/ESRNN.py
esrnn/contrib/utils/__init__.py
esrnn/contrib/utils/config.py
esrnn/contrib/utils/data.py
esrnn/contrib/utils/losses.py
d3m_esrnn-0.1.1.dist-info/LICENSE
d3m_esrnn-0.1.1.dist-info/METADATA
d3m_esrnn-0.1.1.dist-info/WHEEL
d3m_esrnn-0.1.1.dist-info/entry_points.txt
d3m_esrnn-0.1.1.dist-info/top_level.txt
d3m_esrnn-0.1.1.dist-info/RECORD
